spikeinterface_pipelines/__init__.py
spikeinterface_pipelines/global_params.py
spikeinterface_pipelines/logger.py
spikeinterface_pipelines/pipeline.py
spikeinterface_pipelines/curation/__init__.py
spikeinterface_pipelines/curation/curation.py
spikeinterface_pipelines/curation/params.py
spikeinterface_pipelines/postprocessing/__init__.py
spikeinterface_pipelines/postprocessing/params.py
spikeinterface_pipelines/postprocessing/postprocessing.py
spikeinterface_pipelines/preprocessing/__init__.py
spikeinterface_pipelines/preprocessing/params.py
spikeinterface_pipelines/preprocessing/preprocessing.py
spikeinterface_pipelines/spikesorting/__init__.py
spikeinterface_pipelines/spikesorting/params.py
spikeinterface_pipelines/spikesorting/spikesorting.py
spikeinterface_pipelines/visualization/__init__.py
spikeinterface_pipelines/visualization/params.py
spikeinterface_pipelines/visualization/visualization.py
spikeinterface_pipelines-0.0.11.dist-info/LICENSE
spikeinterface_pipelines-0.0.11.dist-info/METADATA
spikeinterface_pipelines-0.0.11.dist-info/WHEEL
spikeinterface_pipelines-0.0.11.dist-info/top_level.txt
spikeinterface_pipelines-0.0.11.dist-info/RECORD
