Metadata-Version: 2.1
Name: spikeinterface_pipelines
Version: 0.0.11
Summary: Collection of standardized analysis pipelines based on SpikeInterfacee.
Author-email: Alessio Buccino <alessiop.buccino@gmail.com>, Jeremy Magland <jmagland@flatironinstitute.org>, Luiz Tauffer <luiz.tauffer@catalystneuro.com>
Project-URL: homepage, https://github.com/SpikeInterface/spikeinterface_pipelines
Project-URL: documentation, https://github.com/SpikeInterface/spikeinterface_pipelines
Project-URL: repository, https://github.com/SpikeInterface/spikeinterface_pipelines
Keywords: spikeinterface,spike sorting,electrophysiology,neuroscience
Requires-Python: >=3.8
License-File: LICENSE
Requires-Dist: spikeinterface[full,widgets] >=0.100.0
Requires-Dist: neo >=0.12.0
Requires-Dist: pydantic >=2.4.2
Requires-Dist: sortingview >=0.13.1
Requires-Dist: kachery-cloud >=0.4.7
